jpcm/__init__.py
jpcm/core/core.py
jpcm/core/func.py
jpcm/core/maps.py
jpcm/core/readme.py
jpcm/draw/draw.py
jpcm/load/load.py
jpcm/utils/utils.py
jpcm-0.1.27.dist-info/licenses/LICENSE
jpcm-0.1.27.dist-info/METADATA
jpcm-0.1.27.dist-info/WHEEL
jpcm-0.1.27.dist-info/top_level.txt
jpcm-0.1.27.dist-info/RECORD
