Metadata-Version: 2.4
Name: jpcm
Version: 0.1.27
Summary: A perceptually uniform colormap generator equipped with a traditional-ish Japanese color palette. Allows unique colormap generation and integration with ML experiment workflows.
Home-page: https://github.com/akhilsadam/perceptual-jp-colormaps
Author: Akhil Sadam
Author-email: sadam.akhil@gmail.com
Project-URL: Bug Tracker, https://github.com/akhilsadam/perceptual-jp-colormaps/issues
Classifier: Programming Language :: Python :: 3
Classifier: License :: OSI Approved :: MIT License
Classifier: Operating System :: OS Independent
Requires-Python: >=3.8
License-File: LICENSE
Requires-Dist: setuptools>=42
Requires-Dist: wheel
Requires-Dist: colour-science>=0.3.16
Requires-Dist: numpy>=1.23.5
Requires-Dist: scipy
Requires-Dist: pynverse
Requires-Dist: matplotlib>=3.3.4
Requires-Dist: networkx>=2.5
Requires-Dist: ffmpeg-python
Requires-Dist: tqdm
Requires-Dist: einops
Dynamic: license-file
